pyableton/Ableton.py
pyableton/AbletonComponent.py
pyableton/ClipTimeable.py
pyableton/FollowAction.py
pyableton/Grid.py
pyableton/LiveSet.py
pyableton/Midi.py
pyableton/Mixer.py
pyableton/Scene.py
pyableton/Sequencer.py
pyableton/Track.py
pyableton/__init__.py
pyableton/constants.py
pyableton-0.0.15.dist-info/METADATA
pyableton-0.0.15.dist-info/WHEEL
pyableton-0.0.15.dist-info/top_level.txt
pyableton-0.0.15.dist-info/RECORD
