Metadata-Version: 2.1
Name: pyableton
Version: 0.0.15
Summary: A compact package to parse Ableton .als files
Project-URL: Homepage, https://github.com/maranedah/pyableton
Project-URL: Bug Tracker, https://github.com/maranedah/pyableton/issues
Classifier: Programming Language :: Python :: 3
Classifier: License :: OSI Approved :: MIT License
Classifier: Operating System :: OS Independent
Requires-Python: >=3.10
Requires-Dist: muspy >=0.5.0
Requires-Dist: pandas >=2.0.0
